APGD/APGD.py
APGD/__init__.py
APGD-0.1.dist-info/LICENSE
APGD-0.1.dist-info/METADATA
APGD-0.1.dist-info/WHEEL
APGD-0.1.dist-info/top_level.txt
APGD-0.1.dist-info/RECORD
