Metadata-Version: 2.1
Name: APGD
Version: 0.1
Summary: Accelerated Proximal Gradient Descent (APGD) algorithm to solve the penalized regression models
Home-page: https://github.com/tobefuture/APGD
Author: Ling Zhang
Author-email: lingzhan@mtu.edu
License: UNKNOWN
Platform: UNKNOWN
Classifier: Programming Language :: Python :: 3
Classifier: License :: OSI Approved :: MIT License
Classifier: Operating System :: OS Independent
Requires-Python: >=3.6
License-File: LICENSE
Requires-Dist: numpy
Requires-Dist: pandas
Requires-Dist: cvxpy
Requires-Dist: networkx
Requires-Dist: sklearn
